ilinq/__init__.py
ilinq/igroup.py
ilinq/ilinq.py
ilinq/ilookup.py
ilinq-0.4.2.dist-info/LICENSE.txt
ilinq-0.4.2.dist-info/METADATA
ilinq-0.4.2.dist-info/WHEEL
ilinq-0.4.2.dist-info/top_level.txt
ilinq-0.4.2.dist-info/RECORD
